pyfiletree/__init__.py
pyfiletree/ftree.py
pyfiletree/test.py
pyfiletree-0.1.6.dist-info/LICENSE
pyfiletree-0.1.6.dist-info/LICENSE.txt
pyfiletree-0.1.6.dist-info/METADATA
pyfiletree-0.1.6.dist-info/WHEEL
pyfiletree-0.1.6.dist-info/top_level.txt
pyfiletree-0.1.6.dist-info/RECORD
