Metadata-Version: 2.1
Name: pyfiletree
Version: 0.1.6
Summary: Read/Write python files
Home-page: UNKNOWN
Author: Sam
License: MIT
Platform: UNKNOWN
Provides-Extra: dev
Requires-Dist: pytest (>=4.4.1) ; extra == 'dev'
